setup.py
flask_ypaginate.egg-info/PKG-INFO
flask_ypaginate.egg-info/SOURCES.txt
flask_ypaginate.egg-info/dependency_links.txt
flask_ypaginate.egg-info/namespace_packages.txt
flask_ypaginate.egg-info/not-zip-safe
flask_ypaginate.egg-info/requires.txt
flask_ypaginate.egg-info/top_level.txt
flaskext/__init__.py
flaskext/ypaginate.py
test/test.py