Metadata-Version: 1.1
Name: flask-ypaginate
Version: 0.1.2
Summary: Pagination for Flask
Home-page: https://github.com/yanhan/flask-paginate
Author: Pang Yan Han
Author-email: pangyanhan@gmail.com
License: BSD
Platform: any
Classifier: Environment :: Web Environment
Classifier: Intended Audience :: Developers
Classifier: License :: OSI Approved :: BSD License
Classifier: Operating System :: OS Independent
Classifier: Programming Language :: Python
Classifier: Topic :: Internet :: WWW/HTTP :: Dynamic Content
Classifier: Topic :: Software Development :: Libraries :: Python Modules
